lexoffice/__init__.py
lexoffice/api.py
lexoffice/datatypes.py
lexoffice/exceptions.py
lexoffice_api-0.0.4.dist-info/LICENSE
lexoffice_api-0.0.4.dist-info/METADATA
lexoffice_api-0.0.4.dist-info/WHEEL
lexoffice_api-0.0.4.dist-info/top_level.txt
lexoffice_api-0.0.4.dist-info/RECORD
