Metadata-Version: 2.1
Name: lexoffice-api
Version: 0.0.4
Summary: Python library for interacting with the Public API of Lexoffice
Home-page: https://github.com/maikerlab/lexoffice_api
Author: Maik Lorenz
Author-email: lorenz.maik@web.de
Project-URL: Bug Tracker, https://github.com/maikerlab/lexoffice_api/issues
Classifier: Programming Language :: Python :: 3
Classifier: License :: OSI Approved :: MIT License
Classifier: Operating System :: OS Independent
License-File: LICENSE
